{"card_name": "Failure of Logistics", "color": "G", "rarity": "uncommon", "type": "Enchantment Battle \u2013 Curse Siege", "number": 124, "color_identity": "G", "cost": "{4}{G}", "rules_text": "Enchant player [i](they must be the defending player)[/i]\nAt the beginning of enchanted player\u2019s upkeep, that player puts a stun counter on two untapped lands they control. Put a curse counter on this battle.", "pt": "5", "special_text": "", "shape": "double faced", "set": "DTH", "loyalty": "", "card_name2": "Overwhelming Encirclement", "color2": "G", "type2": "Sorcery", "cost2": "", "rules_text2": "Return X target permanent cards from your graveyard and/or exile to your hand, where X is the number of curse counters on this battle as it transformed.", "pt2": "", "special_text2": "", "loyalty2": "", "notes": ""}